[{"result":"Sunrisers won by 5 wickets (with 35 balls remaining)","name":"Josh Philippe ","run":"32","ball":"31","fours":"-","sixes":"4","strikerate":"0","opponent":"Sunrisers Hyderabad","date":"Oct 31 2020","venue":"Sharjah"},{"result":"Mum Indians won by 5 wickets (with 5 balls remaining)","name":"Josh Philippe ","run":"33","ball":"24","fours":"-","sixes":"4","strikerate":"1","opponent":"Mumbai Indians","date":"Oct 28 2020","venue":"Abu Dhabi"},{"result":"Capitals won by 6 wickets (with 6 balls remaining)","name":"Josh Philippe ","run":"12","ball":"17","fours":"-","sixes":"1","strikerate":"0","opponent":"Delhi Capitals","date":"Nov 2 2020","venue":"Abu Dhabi"}]